XStatic_svgedit-7.2.0.2-py3.10-nspkg.pth
xstatic/pkg/svgedit/__init__.py
xstatic/pkg/svgedit/data/packages/svgcanvas/blur-event.js
xstatic/pkg/svgedit/data/packages/svgcanvas/clear.js
xstatic/pkg/svgedit/data/packages/svgcanvas/coords.js
xstatic/pkg/svgedit/data/packages/svgcanvas/copy-elem.js
xstatic/pkg/svgedit/data/packages/svgcanvas/dataStorage.js
xstatic/pkg/svgedit/data/packages/svgcanvas/draw.js
xstatic/pkg/svgedit/data/packages/svgcanvas/elem-get-set.js
xstatic/pkg/svgedit/data/packages/svgcanvas/event.js
xstatic/pkg/svgedit/data/packages/svgcanvas/history.js
xstatic/pkg/svgedit/data/packages/svgcanvas/historyrecording.js
xstatic/pkg/svgedit/data/packages/svgcanvas/json.js
xstatic/pkg/svgedit/data/packages/svgcanvas/layer.js
xstatic/pkg/svgedit/data/packages/svgcanvas/math.js
xstatic/pkg/svgedit/data/packages/svgcanvas/namespaces.js
xstatic/pkg/svgedit/data/packages/svgcanvas/package-lock.json
xstatic/pkg/svgedit/data/packages/svgcanvas/package.json
xstatic/pkg/svgedit/data/packages/svgcanvas/paint.js
xstatic/pkg/svgedit/data/packages/svgcanvas/paste-elem.js
xstatic/pkg/svgedit/data/packages/svgcanvas/path-actions.js
xstatic/pkg/svgedit/data/packages/svgcanvas/path-method.js
xstatic/pkg/svgedit/data/packages/svgcanvas/path.js
xstatic/pkg/svgedit/data/packages/svgcanvas/recalculate.js
xstatic/pkg/svgedit/data/packages/svgcanvas/rollup.config.js
xstatic/pkg/svgedit/data/packages/svgcanvas/sanitize.js
xstatic/pkg/svgedit/data/packages/svgcanvas/select.js
xstatic/pkg/svgedit/data/packages/svgcanvas/selected-elem.js
xstatic/pkg/svgedit/data/packages/svgcanvas/selection.js
xstatic/pkg/svgedit/data/packages/svgcanvas/svg-exec.js
xstatic/pkg/svgedit/data/packages/svgcanvas/svgcanvas.js
xstatic/pkg/svgedit/data/packages/svgcanvas/svgroot.js
xstatic/pkg/svgedit/data/packages/svgcanvas/text-actions.js
xstatic/pkg/svgedit/data/packages/svgcanvas/touch.js
xstatic/pkg/svgedit/data/packages/svgcanvas/undo.js
xstatic/pkg/svgedit/data/packages/svgcanvas/units.js
XStatic_svgedit-7.2.0.2.dist-info/LICENSE
XStatic_svgedit-7.2.0.2.dist-info/METADATA
XStatic_svgedit-7.2.0.2.dist-info/WHEEL
XStatic_svgedit-7.2.0.2.dist-info/namespace_packages.txt
XStatic_svgedit-7.2.0.2.dist-info/top_level.txt
XStatic_svgedit-7.2.0.2.dist-info/RECORD
