Metadata-Version: 2.1
Name: XStatic-svgedit
Version: 7.2.0.2
Summary: svgedit 7.2.0 (XStatic packaging standard)
Home-page: https://github.com/SVG-Edit/svgedit
Maintainer: Roger Haase
Maintainer-email: haaserd@gmail.com
License: (same as svgedit)
Keywords: svgedit xstatic
Platform: any
License-File: LICENSE
